{"sportId":3,"last":46099534,"league":[{"id":246,"events":[{"id":480374634,"starts":"2015-07-09T23:05:00Z","home":"Pittsburgh Pirates","away":"St. Louis Cardinals","rotNum":"9901","liveStatus":1,"status":"O","parlayRestriction":2},{"id":480374655,"starts":"2015-07-09T23:05:00Z","home":"Pittsburgh Pirates","away":"St. Louis Cardinals","rotNum":"9091","liveStatus":1,"status":"O","parlayRestriction":2},{"id":480374999,"starts":"2015-07-09T23:10:00Z","home":"Miami Marlins","away":"Cincinnati Reds","rotNum":"9903","liveStatus":1,"status":"O","parlayRestriction":2},{"id":480375010,"starts":"2015-07-09T23:10:00Z","home":"Miami Marlins","away":"Cincinnati Reds","rotNum":"9903","liveStatus":1,"status":"O","parlayRestriction":2},{"id":480375037,"starts":"2015-07-10T00:40:00Z","home":"Colorado Rockies","away":"Atlanta Braves","rotNum":"9905","liveStatus":1,"status":"O","parlayRestriction":2},{"id":480375049,"starts":"2015-07-10T00:40:00Z","home":"Colorado Rockies","away":"Atlanta Braves","rotNum":"9905","liveStatus":1,"status":"O","parlayRestriction":2},{"id":480375069,"starts":"2015-07-10T02:10:00Z","home":"Los Angeles Dodgers","away":"Philadelphia Phillies","rotNum":"9907","liveStatus":1,"status":"O","parlayRestriction":2},{"id":480375082,"starts":"2015-07-10T02:10:00Z","home":"Los Angeles Dodgers","away":"Philadelphia Phillies","rotNum":"9907","liveStatus":1,"status":"O","parlayRestriction":2},{"id":480375219,"starts":"2015-07-09T18:10:00Z","home":"Chicago White Sox","away":"Toronto Blue Jays","rotNum":"9911","liveStatus":1,"status":"O","parlayRestriction":2},{"id":480375288,"starts":"2015-07-09T23:10:00Z","home":"Cleveland Indians","away":"Houston Astros","rotNum":"9915","liveStatus":1,"status":"O","parlayRestriction":2},{"id":480375310,"starts":"2015-07-09T23:10:00Z","home":"Cleveland Indians","away":"Houston Astros","rotNum":"9915","liveStatus":1,"status":"O","parlayRestriction":2},{"id":480375341,"starts":"2015-07-10T00:10:00Z","home":"Minnesota Twins","away":"Detroit Tigers","rotNum":"9917","liveStatus":1,"status":"O","parlayRestriction":2},{"id":480375364,"starts":"2015-07-10T00:10:00Z","home":"Minnesota Twins","away":"Detroit Tigers","rotNum":"9917","liveStatus":1,"status":"O","parlayRestriction":2},{"id":480375383,"starts":"2015-07-10T02:10:00Z","home":"Seattle Mariners","away":"LAA Angels","rotNum":"9919","liveStatus":1,"status":"O","parlayRestriction":2},{"id":480139580,"starts":"2015-07-08T23:05:00Z","home":"Washington Nationals","away":"Cincinnati Reds","rotNum":"9955","liveStatus":1,"status":"I","parlayRestriction":2},{"id":480139556,"starts":"2015-07-08T23:05:00Z","home":"Washington Nationals","away":"Cincinnati Reds","rotNum":"9955","liveStatus":1,"status":"I","parlayRestriction":2},{"id":480375401,"starts":"2015-07-10T02:10:00Z","home":"Seattle Mariners","away":"LAA Angels","rotNum":"9919","liveStatus":1,"status":"O","parlayRestriction":2},{"id":480554588,"starts":"2015-07-10T23:05:00Z","home":"Pittsburgh Pirates","away":"St. Louis Cardinals","rotNum":"9951","liveStatus":1,"status":"O","parlayRestriction":2},{"id":480554598,"starts":"2015-07-10T23:05:00Z","home":"Pittsburgh Pirates","away":"St. Louis Cardinals","rotNum":"9951","liveStatus":1,"status":"O","parlayRestriction":2},{"id":480554608,"starts":"2015-07-10T23:10:00Z","home":"Miami Marlins","away":"Cincinnati Reds","rotNum":"9953","liveStatus":1,"status":"O","parlayRestriction":2},{"id":480554624,"starts":"2015-07-10T23:10:00Z","home":"Miami Marlins","away":"Cincinnati Reds","rotNum":"9953","liveStatus":1,"status":"O","parlayRestriction":2},{"id":480554632,"starts":"2015-07-10T23:10:00Z","home":"New York Mets","away":"Arizona Diamondbacks","rotNum":"9955","liveStatus":1,"status":"O","parlayRestriction":2},{"id":480554675,"starts":"2015-07-10T23:10:00Z","home":"New York Mets","away":"Arizona Diamondbacks","rotNum":"9955","liveStatus":1,"status":"O","parlayRestriction":2},{"id":480554686,"starts":"2015-07-11T00:10:00Z","home":"Colorado Rockies","away":"Atlanta Braves","rotNum":"9957","liveStatus":1,"status":"O","parlayRestriction":2},{"id":480554700,"starts":"2015-07-11T00:10:00Z","home":"Colorado Rockies","away":"Atlanta Braves","rotNum":"9957","liveStatus":1,"status":"O","parlayRestriction":2},{"id":480554717,"starts":"2015-07-11T02:10:00Z","home":"Los Angeles Dodgers","away":"Milwaukee Brewers","rotNum":"9959","liveStatus":1,"status":"O","parlayRestriction":2},{"id":480554730,"starts":"2015-07-11T02:10:00Z","home":"Los Angeles Dodgers","away":"Milwaukee Brewers","rotNum":"9959","liveStatus":1,"status":"O","parlayRestriction":2},{"id":480554739,"starts":"2015-07-11T02:15:00Z","home":"San Francisco Giants","away":"Philadelphia Phillies","rotNum":"9961","liveStatus":1,"status":"O","parlayRestriction":2},{"id":480554750,"starts":"2015-07-11T02:15:00Z","home":"San Francisco Giants","away":"Philadelphia Phillies","rotNum":"9961","liveStatus":1,"status":"O","parlayRestriction":2},{"id":480554770,"starts":"2015-07-10T23:10:00Z","home":"Tampa Bay Rays","away":"Houston Astros","rotNum":"9963","liveStatus":1,"status":"O","parlayRestriction":2},{"id":480554782,"starts":"2015-07-10T23:10:00Z","home":"Tampa Bay Rays","away":"Houston Astros","rotNum":"9963","liveStatus":1,"status":"O","parlayRestriction":2},{"id":480554825,"starts":"2015-07-10T23:10:00Z","home":"Cleveland Indians","away":"Oakland Athletics","rotNum":"9966","liveStatus":1,"status":"O","parlayRestriction":2},{"id":480554844,"starts":"2015-07-10T23:10:00Z","home":"Boston Red Sox","away":"New York Yankees","rotNum":"9967","liveStatus":1,"status":"O","parlayRestriction":2},{"id":480554868,"starts":"2015-07-10T23:10:00Z","home":"Boston Red Sox","away":"New York Yankees","rotNum":"9967","liveStatus":1,"status":"O","parlayRestriction":2},{"id":480554890,"starts":"2015-07-11T00:10:00Z","home":"Kansas City Royals","away":"Toronto Blue Jays","rotNum":"9969","liveStatus":1,"status":"O","parlayRestriction":2},{"id":480554903,"starts":"2015-07-11T00:10:00Z","home":"Kansas City Royals","away":"Toronto Blue Jays","rotNum":"9969","liveStatus":1,"status":"O","parlayRestriction":2},{"id":480554921,"starts":"2015-07-11T00:10:00Z","home":"Minnesota Twins","away":"Detroit Tigers","rotNum":"9971","liveStatus":1,"status":"O","parlayRestriction":2},{"id":480554935,"starts":"2015-07-11T00:10:00Z","home":"Minnesota Twins","away":"Detroit Tigers","rotNum":"9971","liveStatus":1,"status":"O","parlayRestriction":2},{"id":480554941,"starts":"2015-07-11T02:10:00Z","home":"Seattle Mariners","away":"LAA Angels","rotNum":"9973","liveStatus":1,"status":"O","parlayRestriction":2},{"id":480554955,"starts":"2015-07-11T02:10:00Z","home":"Seattle Mariners","away":"LAA Angels","rotNum":"9973","liveStatus":1,"status":"O","parlayRestriction":2},{"id":480555002,"starts":"2015-07-10T20:05:00Z","home":"Chicago Cubs","away":"Chicago White Sox","rotNum":"9975","liveStatus":1,"status":"O","parlayRestriction":2},{"id":480555020,"starts":"2015-07-10T20:05:00Z","home":"Chicago Cubs","away":"Chicago White Sox","rotNum":"9975","liveStatus":1,"status":"O","parlayRestriction":2},{"id":480555033,"starts":"2015-07-10T23:05:00Z","home":"Baltimore Orioles","away":"Washington Nationals","rotNum":"9977","liveStatus":1,"status":"O","parlayRestriction":2},{"id":480555047,"starts":"2015-07-10T23:05:00Z","home":"Baltimore Orioles","away":"Washington Nationals","rotNum":"9977","liveStatus":1,"status":"O","parlayRestriction":2},{"id":480555068,"starts":"2015-07-11T00:05:00Z","home":"Texas Rangers","away":"San Diego Padres","rotNum":"9979","liveStatus":1,"status":"O","parlayRestriction":2},{"id":480555213,"starts":"2015-07-11T00:05:00Z","home":"Texas Rangers","away":"San Diego Padres","rotNum":"9979","liveStatus":1,"status":"O","parlayRestriction":2},{"id":480375118,"starts":"2015-07-09T17:05:00Z","home":"New York Yankees","away":"Oakland Athletics","rotNum":"9909","liveStatus":1,"status":"H","parlayRestriction":2},{"id":480375240,"starts":"2015-07-09T18:10:00Z","home":"Chicago White Sox","away":"Toronto Blue Jays","rotNum":"9911","liveStatus":1,"status":"H","parlayRestriction":2},{"id":480375272,"starts":"2015-07-09T18:10:00Z","home":"Kansas City Royals","away":"Tampa Bay Rays","rotNum":"9913","liveStatus":1,"status":"H","parlayRestriction":2},{"id":480375257,"starts":"2015-07-09T18:10:00Z","home":"Kansas City Royals","away":"Tampa Bay Rays","rotNum":"9913","liveStatus":1,"status":"I","parlayRestriction":2},{"id":480375141,"starts":"2015-07-09T17:05:00Z","home":"New York Yankees","away":"Oakland Athletics","rotNum":"9909","liveStatus":1,"status":"I","parlayRestriction":2}]}]}